neo/__init__.py
neo/cli.py
neo/clis/__init__.py
neo/clis/attach.py
neo/clis/base.py
neo/clis/create.py
neo/clis/log.py
neo/clis/login.py
neo/clis/logout.py
neo/clis/ls.py
neo/clis/rm.py
neo/clis/update.py
neo/clis/vm.py
neo/libs/__init__.py
neo/libs/image.py
neo/libs/interactive_ssh_utils.py
neo/libs/lambdafunc.py
neo/libs/login.py
neo/libs/ncurses.py
neo/libs/network.py
neo/libs/orchestration.py
neo/libs/prompt.py
neo/libs/storage.py
neo/libs/utils.py
neo/libs/vm.py
neo/libs/templates/repo.yml
neo_cli-0.9.7.dist-info/LICENSE
neo_cli-0.9.7.dist-info/METADATA
neo_cli-0.9.7.dist-info/WHEEL
neo_cli-0.9.7.dist-info/entry_points.txt
neo_cli-0.9.7.dist-info/top_level.txt
neo_cli-0.9.7.dist-info/RECORD
