Metadata-Version: 2.1
Name: neo-cli
Version: 0.9.7
Summary: A NEO command line tools
Home-page: https://github.com/BiznetGIO/neo-cli
Author: BiznetGio
Author-email: support@biznetgio.com
License: MIT license
Keywords: cli
Classifier: Intended Audience :: Developers
Classifier: Topic :: Utilities
Classifier: License :: OSI Approved :: MIT License
Classifier: Natural Language :: English
Classifier: Operating System :: OS Independent
Classifier: Programming Language :: Python
Classifier: Programming Language :: Python :: 3.6
License-File: LICENSE
Requires-Dist: dill ==0.3.6
Requires-Dist: bitmath ==1.3.3.1
Requires-Dist: python-neutronclient ==7.8.0
Requires-Dist: prompt-toolkit ==1.0.18
Requires-Dist: python-glanceclient ==3.6.0
Requires-Dist: requests ==2.28.2
Requires-Dist: paramiko ==2.12.0
Requires-Dist: tabulate ==0.9.0
Requires-Dist: keystoneauth1 ==5.1.2
Requires-Dist: openstacksdk ==1.0.1
Requires-Dist: python-heatclient ==2.5.1
Requires-Dist: coloredlogs ==15.0.1
Requires-Dist: setuptools ==67.2.0
Requires-Dist: scp ==0.14.5
Requires-Dist: npyscreen ==4.10.5
Requires-Dist: docopt ==0.6.2
Requires-Dist: python-dotenv ==0.21.1
Requires-Dist: GitPython ==3.1.30
Requires-Dist: python-keystoneclient ==4.5.0
Requires-Dist: python-novaclient ==18.2.0
Requires-Dist: python-cinderclient ==9.2.0
Requires-Dist: PyYAML ==6.0.1
Requires-Dist: toml ==0.10.2
